everyreview/__init__.py
everyreview/settings.py
everyreview/urls.py
everyreview/wsgi.py
review/__init__.py
review/admin.py
review/apps.py
review/models.py
review/tests.py
review/urls.py
review/views.py
review/migrations/0001_initial.py
review/migrations/__init__.py
everyreview2-0.1.dist-info/METADATA
everyreview2-0.1.dist-info/WHEEL
everyreview2-0.1.dist-info/top_level.txt
everyreview2-0.1.dist-info/RECORD
