Metadata-Version: 2.1
Name: everyreview2
Version: 0.1
Summary: everyreview2
Home-page: https://github.com/urbanGY/everyreview2
Author: urbanGY
Author-email: sfsfkj@gmail.com
License: UNKNOWN
Download-URL: https://github.com/urbanGY/everyreview2/0.0.tar.gz
Keywords: everyreview2
Platform: UNKNOWN
Classifier: Programming Language :: Python :: 3
Classifier: Programming Language :: Python :: 3.2
Classifier: Programming Language :: Python :: 3.3
Classifier: Programming Language :: Python :: 3.4
Classifier: Programming Language :: Python :: 3.5
Classifier: Programming Language :: Python :: 3.6
Classifier: Programming Language :: Python :: 3.7
Requires-Python: >=3
